{
  "name": "collision",
  "scenarios": [
    {
      "state": {
        "time": 0.0,
        "crashed": false,
        "ego_x": 6080.3056640625,
        "ego_y": 11.999930381774902,
        "ego_heading": 1.050622813636437e-05,
        "ego_speed": 29.878334045410156,
        "ego_lane": 3,
        "npc0_x": 6091.6318359375,
        "npc0_y": 4.0,
        "npc0_heading": 1.0576346198831743e-07,
        "npc0_speed": 22.775983810424805,
        "npc0_lane": 1,
        "npc1_x": 6097.51123046875,
        "npc1_y": 8.0,
        "npc1_heading": 0.0,
        "npc1_speed": 22.631698608398438,
        "npc1_lane": 2,
        "npc2_x": 6062.6640625,
        "npc2_y": 0.0,
        "npc2_heading": 0.0,
        "npc2_speed": 21.691923141479492,
        "npc2_lane": 0,
        "npc3_x": 6106.88818359375,
        "npc3_y": 11.999998092651367,
        "npc3_heading": 1.815284349504509e-07,
        "npc3_speed": 23.972679138183594,
        "npc3_lane": 3,
        "npc4_x": 5959.8349609375,
        "npc4_y": 7.999998569488525,
        "npc4_heading": 1.4847765328340756e-07,
        "npc4_speed": 22.931407928466797,
        "npc4_lane": 2,
        "npc5_x": 5956.3876953125,
        "npc5_y": 11.999998092651367,
        "npc5_heading": 1.9089463876298396e-07,
        "npc5_speed": 23.370258331298828,
        "npc5_lane": 3,
        "npc6_x": 6207.55615234375,
        "npc6_y": 3.999999761581421,
        "npc6_heading": 7.064050322469484e-08,
        "npc6_speed": 22.843069076538086,
        "npc6_lane": 1,
        "npc7_x": 5951.23681640625,
        "npc7_y": 0.0,
        "npc7_heading": 0.0,
        "npc7_speed": 21.697052001953125,
        "npc7_lane": 0
      },
      "observation": [
        [
          1.0,
          1.0,
          0.7499956488609314,
          0.3734791874885559,
          3.923857548215892e-06
        ],
        [
          1.0,
          0.05663085728883743,
          -0.4999956488609314,
          -0.08877938240766525,
          -3.893746452376945e-06
        ],
        [
          1.0,
          0.0860278308391571,
          -0.2499956488609314,
          -0.0905829444527626,
          -3.923857548215892e-06
        ],
        [
          1.0,
          0.13291259109973907,
          4.231929779052734e-06,
          -0.07382068783044815,
          -3.869461124850204e-06
        ],
        [
          1.0,
          0.6362524032592773,
          -0.4999956488609314,
          -0.08794081211090088,
          -3.903687229467323e-06
        ]
      ],
      "action_weights": {
        "left": 2.0
      }
    },
    {
      "state": {
        "time": 0.0,
        "crashed": false,
        "ego_x": 3468.5166015625,
        "ego_y": 12.0,
        "ego_heading": 1.0438505881893434e-07,
        "ego_speed": 29.99999237060547,
        "ego_lane": 3,
        "npc0_x": 3463.783447265625,
        "npc0_y": 0.0,
        "npc0_heading": 0.0,
        "npc0_speed": 21.456403732299805,
        "npc0_lane": 0,
        "npc1_x": 3477.864501953125,
        "npc1_y": 4.0,
        "npc1_heading": 0.0,
        "npc1_speed": 20.9979248046875,
        "npc1_lane": 1,
        "npc2_x": 3482.94482421875,
        "npc2_y": 8.0,
        "npc2_heading": 0.0,
        "npc2_speed": 21.812118530273438,
        "npc2_lane": 2,
        "npc3_x": 3535.775390625,
        "npc3_y": 0.0,
        "npc3_heading": 0.0,
        "npc3_speed": 21.501129150390625,
        "npc3_lane": 0,
        "npc4_x": 3395.781494140625,
        "npc4_y": 4.000035762786865,
        "npc4_heading": -5.021367542212829e-06,
        "npc4_speed": 21.520606994628906,
        "npc4_lane": 1,
        "npc5_x": 3395.559326171875,
        "npc5_y": 12.0,
        "npc5_heading": 0.0,
        "npc5_speed": 21.084028244018555,
        "npc5_lane": 3,
        "npc6_x": 3357.60986328125,
        "npc6_y": 0.0,
        "npc6_heading": 0.0,
        "npc6_speed": 21.138978958129883,
        "npc6_lane": 0,
        "npc7_x": 3334.60205078125,
        "npc7_y": 11.99999713897705,
        "npc7_heading": 2.9307653903742903e-07,
        "npc7_speed": 19.258949279785156,
        "npc7_lane": 3
      },
      "observation": [
        [
          1.0,
          1.0,
          0.75,
          0.37499991059303284,
          3.91443890634946e-08
        ],
        [
          1.0,
          -0.023665770888328552,
          -0.75,
          -0.10679485648870468,
          -3.91443890634946e-08
        ],
        [
          1.0,
          0.046739500015974045,
          -0.5,
          -0.11252584308385849,
          -3.91443890634946e-08
        ],
        [
          1.0,
          0.07214111089706421,
          -0.25,
          -0.10234842449426651,
          -3.91443890634946e-08
        ],
        [
          1.0,
          0.33629393577575684,
          -0.75,
          -0.1062357947230339,
          -3.91443890634946e-08
        ]
      ],
      "action_weights": {
        "left": 2.0
      }
    },
    {
      "state": {
        "time": 0.0,
        "crashed": false,
        "ego_x": 2446.55810546875,
        "ego_y": 2.9820852432749234e-05,
        "ego_heading": -4.010871180071263e-06,
        "ego_speed": 24.858253479003906,
        "ego_lane": 0,
        "npc0_x": 2445.8642578125,
        "npc0_y": 12.0,
        "npc0_heading": 0.0,
        "npc0_speed": 21.960298538208008,
        "npc0_lane": 3,
        "npc1_x": 2459.125732421875,
        "npc1_y": 8.0,
        "npc1_heading": 0.0,
        "npc1_speed": 19.963333129882812,
        "npc1_lane": 2,
        "npc2_x": 2484.31787109375,
        "npc2_y": -1.223016568019375e-07,
        "npc2_heading": -7.645594024552338e-08,
        "npc2_speed": 20.272321701049805,
        "npc2_lane": 0,
        "npc3_x": 2398.98388671875,
        "npc3_y": 0.0,
        "npc3_heading": 0.0,
        "npc3_speed": 18.62806510925293,
        "npc3_lane": 0,
        "npc4_x": 2398.158447265625,
        "npc4_y": 4.0,
        "npc4_heading": 8.410827945226629e-08,
        "npc4_speed": 20.945016860961914,
        "npc4_lane": 1,
        "npc5_x": 2511.6875,
        "npc5_y": 4.000000953674316,
        "npc5_heading": -1.2375406299725e-07,
        "npc5_speed": 20.997087478637695,
        "npc5_lane": 1,
        "npc6_x": 2365.365478515625,
        "npc6_y": 8.0,
        "npc6_heading": 0.0,
        "npc6_speed": 21.06739616394043,
        "npc6_lane": 2,
        "npc7_x": 2536.545166015625,
        "npc7_y": 8.000001907348633,
        "npc7_heading": -2.3604491161677288e-07,
        "npc7_speed": 21.265226364135742,
        "npc7_lane": 2
      },
      "observation": [
        [
          1.0,
          1.0,
          1.8638032770468271e-06,
          0.31072816252708435,
          -1.2462907079680008e-06
        ],
        [
          1.0,
          -0.0034692382905632257,
          0.749998152256012,
          -0.03622443601489067,
          1.2462907079680008e-06
        ],
        [
          1.0,
          0.0628381296992302,
          0.4999981224536896,
          -0.06118650361895561,
          1.2462907079680008e-06
        ],
        [
          1.0,
          0.18879882991313934,
          -1.8714471252678777e-06,
          -0.05732414871454239,
          1.2269164244571584e-06
        ],
        [
          1.0,
          0.3256469666957855,
          0.24999819695949554,
          -0.04826457425951958,
          1.2138096963099088e-06
        ]
      ],
      "action_weights": {
        "right": 2.0
      }
    },
    {
      "state": {
        "time": 0.0,
        "crashed": false,
        "ego_x": 3361.27734375,
        "ego_y": 0.0419907346367836,
        "ego_heading": -0.0050378525629639626,
        "ego_speed": 25.825225830078125,
        "ego_lane": 0,
        "npc0_x": 3371.96630859375,
        "npc0_y": 8.0,
        "npc0_heading": 0.0,
        "npc0_speed": 20.767366409301758,
        "npc0_lane": 2,
        "npc1_x": 3345.301025390625,
        "npc1_y": 11.999998092651367,
        "npc1_heading": 2.1628699187203893e-07,
        "npc1_speed": 19.89025115966797,
        "npc1_lane": 3,
        "npc2_x": 3385.513427734375,
        "npc2_y": 0.0,
        "npc2_heading": 0.0,
        "npc2_speed": 20.52128791809082,
        "npc2_lane": 0,
        "npc3_x": 3397.6435546875,
        "npc3_y": 4.000001430511475,
        "npc3_heading": -1.5677997566854174e-07,
        "npc3_speed": 21.437040328979492,
        "npc3_lane": 1,
        "npc4_x": 3302.069091796875,
        "npc4_y": 4.000000476837158,
        "npc4_heading": -9.812321621893716e-08,
        "npc4_speed": 21.09534454345703,
        "npc4_lane": 1,
        "npc5_x": 3428.37109375,
        "npc5_y": 12.0,
        "npc5_heading": 0.0,
        "npc5_speed": 19.954666137695312,
        "npc5_lane": 3,
        "npc6_x": 3439.1484375,
        "npc6_y": 8.0,
        "npc6_heading": 0.0,
        "npc6_speed": 20.80507469177246,
        "npc6_lane": 2,
        "npc7_x": 3283.149658203125,
        "npc7_y": 6.169290855950749e-09,
        "npc7_heading": 2.6537392727732367e-08,
        "npc7_speed": 20.75548553466797,
        "npc7_lane": 0
      },
      "observation": [
        [
          1.0,
          1.0,
          0.002624420914798975,
          0.32281121611595154,
          -0.0016262891003862023
        ],
        [
          1.0,
          0.05344482138752937,
          0.49737557768821716,
          -0.06321914494037628,
          0.0016262891003862023
        ],
        [
          1.0,
          0.12118041515350342,
          -0.002624420914798975,
          -0.06629512459039688,
          0.0016262891003862023
        ],
        [
          1.0,
          0.18183104693889618,
          0.24737566709518433,
          -0.05484822019934654,
          0.001626246958039701
        ],
        [
          1.0,
          0.33546873927116394,
          0.7473756074905396,
          -0.07337789982557297,
          0.0016262891003862023
        ]
      ],
      "action_weights": {
        "right": 2.0
      }
    },
    {
      "state": {
        "time": 0.0,
        "crashed": false,
        "ego_x": 5029.62109375,
        "ego_y": 11.999998092651367,
        "ego_heading": 2.418541669158003e-07,
        "ego_speed": 20.708547592163086,
        "ego_lane": 3,
        "npc0_x": 5031.5947265625,
        "npc0_y": 4.0,
        "npc0_heading": 0.0,
        "npc0_speed": 20.8087215423584,
        "npc0_lane": 1,
        "npc1_x": 5024.47119140625,
        "npc1_y": 7.999999046325684,
        "npc1_heading": 1.3619322203339834e-07,
        "npc1_speed": 21.720918655395508,
        "npc1_lane": 2,
        "npc2_x": 5042.888671875,
        "npc2_y": 12.0,
        "npc2_heading": 0.0,
        "npc2_speed": 21.07444190979004,
        "npc2_lane": 3,
        "npc3_x": 5055.759765625,
        "npc3_y": 0.0,
        "npc3_heading": 0.0,
        "npc3_speed": 20.44559669494629,
        "npc3_lane": 0,
        "npc4_x": 4994.68017578125,
        "npc4_y": 0.0,
        "npc4_heading": 0.0,
        "npc4_speed": 20.429367065429688,
        "npc4_lane": 0,
        "npc5_x": 5101.44482421875,
        "npc5_y": 7.999999523162842,
        "npc5_heading": 1.0697047514440783e-07,
        "npc5_speed": 20.924278259277344,
        "npc5_lane": 2,
        "npc6_x": 5112.486328125,
        "npc6_y": 12.0,
        "npc6_heading": 0.0,
        "npc6_speed": 21.101274490356445,
        "npc6_lane": 3,
        "npc7_x": 5128.42431640625,
        "npc7_y": 4.0,
        "npc7_heading": 0.0,
        "npc7_speed": 20.888139724731445,
        "npc7_lane": 1
      },
      "observation": [
        [
          1.0,
          1.0,
          0.7499998807907104,
          0.258856862783432,
          6.260560780901869e-08
        ],
        [
          1.0,
          0.009868163615465164,
          -0.49999988079071045,
          0.0012521743774414062,
          -6.260560780901869e-08
        ],
        [
          1.0,
          -0.025749512016773224,
          -0.24999994039535522,
          0.012654638849198818,
          -2.5627585387155705e-08
        ],
        [
          1.0,
          0.06633789092302322,
          1.1920928955078125e-07,
          0.0045736790634691715,
          -6.260560780901869e-08
        ],
        [
          1.0,
          0.13069336116313934,
          -0.7499998807907104,
          -0.0032868862617760897,
          -6.260560780901869e-08
        ]
      ],
      "action_weights": {
        "faster": 2.0
      }
    },
    {
      "state": {
        "time": 0.0,
        "crashed": false,
        "ego_x": 3205.9716796875,
        "ego_y": 11.999998092651367,
        "ego_heading": 2.1685173123842105e-07,
        "ego_speed": 25.683494567871094,
        "ego_lane": 3,
        "npc0_x": 3201.817138671875,
        "npc0_y": -1.087169721358805e-06,
        "npc0_heading": -1.4651398316800623e-08,
        "npc0_speed": 20.43451499938965,
        "npc0_lane": 0,
        "npc1_x": 3201.319091796875,
        "npc1_y": 7.999999523162842,
        "npc1_heading": 9.208307005792449e-08,
        "npc1_speed": 20.312063217163086,
        "npc1_lane": 2,
        "npc2_x": 3223.5537109375,
        "npc2_y": 12.0,
        "npc2_heading": 0.0,
        "npc2_speed": 20.413246154785156,
        "npc2_lane": 3,
        "npc3_x": 3244.078369140625,
        "npc3_y": 4.000000953674316,
        "npc3_heading": -1.430267673185881e-07,
        "npc3_speed": 21.47707176208496,
        "npc3_lane": 1,
        "npc4_x": 3144.5625,
        "npc4_y": 4.0,
        "npc4_heading": 1.0024419339060842e-07,
        "npc4_speed": 21.74305534362793,
        "npc4_lane": 1,
        "npc5_x": 3268.470703125,
        "npc5_y": 8.000001907348633,
        "npc5_heading": -2.2350968720274977e-07,
        "npc5_speed": 20.27117919921875,
        "npc5_lane": 2,
        "npc6_x": 3133.94873046875,
        "npc6_y": 12.0,
        "npc6_heading": 0.0,
        "npc6_speed": 21.932655334472656,
        "npc6_lane": 3,
        "npc7_x": 3131.4384765625,
        "npc7_y": 8.000001907348633,
        "npc7_heading": -2.1654818738170434e-07,
        "npc7_speed": 20.508346557617188,
        "npc7_lane": 2
      },
      "observation": [
        [
          1.0,
          1.0,
          0.7499998807907104,
          0.3210436999797821,
          6.961888487921897e-08
        ],
        [
          1.0,
          -0.020772704854607582,
          -0.7499999403953552,
          -0.06561224907636642,
          -7.336131346846742e-08
        ],
        [
          1.0,
          -0.023262938484549522,
          -0.24999991059303284,
          -0.06714289635419846,
          -4.623891669552904e-08
        ],
        [
          1.0,
          0.08791015297174454,
          1.1920928955078125e-07,
          -0.06587810814380646,
          -6.961888487921897e-08
        ],
        [
          1.0,
          0.19053344428539276,
          -0.4999998211860657,
          -0.05258028581738472,
          -1.0801633010260048e-07
        ]
      ],
      "action_weights": {
        "faster": 2.0
      }
    }
  ]
}
